jsonschema2popo/__init__.py
jsonschema2popo/__main__.py
jsonschema2popo/classes.py
jsonschema2popo/jsonschema2popo.py
jsonschema2popo/go/__init__.py
jsonschema2popo/go/go.py
jsonschema2popo/go/go_struct.tmpl
jsonschema2popo/js/__init__.py
jsonschema2popo/js/js.py
jsonschema2popo/js/js_class.tmpl
jsonschema2popo/python/__init__.py
jsonschema2popo/python/python.py
jsonschema2popo/python/python_class.tmpl
JSONSchema2PoPo2-3.0.3.dist-info/LICENSE.txt
JSONSchema2PoPo2-3.0.3.dist-info/METADATA
JSONSchema2PoPo2-3.0.3.dist-info/WHEEL
JSONSchema2PoPo2-3.0.3.dist-info/entry_points.txt
JSONSchema2PoPo2-3.0.3.dist-info/top_level.txt
JSONSchema2PoPo2-3.0.3.dist-info/RECORD
