Metadata-Version: 2.1
Name: JSONSchema2PoPo2
Version: 3.0.3
Summary: Converts a JSON Schema to a Plain Old Python Object class
Home-page: https://github.com/mikedombo/JSONSchema2PoPo2
Author: Michael Dombrowski
Author-email: michael@mikedombrowski.com
License: MIT License
Keywords: python json-schema code-generator
Platform: UNKNOWN
Classifier: Development Status :: 5 - Production/Stable
Classifier: Intended Audience :: Developers
Classifier: License :: OSI Approved :: MIT License
Classifier: Topic :: Software Development :: Build Tools
Classifier: Programming Language :: Python :: 3.4
Classifier: Programming Language :: Python :: 3.5
Classifier: Programming Language :: Python :: 3.6
Classifier: Programming Language :: Python :: 3.7
Classifier: Programming Language :: Python :: 3.8
Classifier: Programming Language :: Python :: 3.9
Classifier: Programming Language :: Python :: 3.10
Classifier: Programming Language :: Python :: Implementation :: PyPy
Requires-Python: >=3.4
Requires-Dist: Jinja2 (>=2.11.3)
Requires-Dist: networkx (==2.4)
Provides-Extra: format_js
Requires-Dist: jsbeautifier ; extra == 'format_js'
Provides-Extra: format_python
Requires-Dist: black ; extra == 'format_python'
